sdsim/__init__.py
sdsim/__main__.py
sdsim/__version__.py
sdsim/sdsim.py
sdsim-0.1.0.dist-info/entry_points.txt
sdsim-0.1.0.dist-info/WHEEL
sdsim-0.1.0.dist-info/METADATA
sdsim-0.1.0.dist-info/licenses/LICENSE.md
sdsim-0.1.0.dist-info/RECORD
