Metadata-Version: 2.1
Name: sdsim
Version: 0.1.0
Summary: a similarity calculatior for stable diffusion checkpoints
License: MIT
Author-email: dowon <ks2515@naver.com>
Requires-Python: >=3.8
Requires-Dist: numpy
Requires-Dist: safetensors
Requires-Dist: torch
Requires-Dist: tqdm
Project-URL: repository, https://github.com/Bing-su/sdsim
